uvmgen/super_define.py
uvmgen/uvmgen.py
uvmgen/cluelib/src/cl_bit_stream.svh
uvmgen/cluelib/src/cl_choice.svh
uvmgen/cluelib/src/cl_collection.svh
uvmgen/cluelib/src/cl_comma_formatter.svh
uvmgen/cluelib/src/cl_common_array.svh
uvmgen/cluelib/src/cl_comparator.svh
uvmgen/cluelib/src/cl_crc.svh
uvmgen/cluelib/src/cl_data_stream.svh
uvmgen/cluelib/src/cl_decimal_formatter.svh
uvmgen/cluelib/src/cl_decimal_min_formatter.svh
uvmgen/cluelib/src/cl_default_comparator.svh
uvmgen/cluelib/src/cl_define.svh
uvmgen/cluelib/src/cl_deque.svh
uvmgen/cluelib/src/cl_deque_descending_iterator.svh
uvmgen/cluelib/src/cl_deque_iterator.svh
uvmgen/cluelib/src/cl_dpi.cc
uvmgen/cluelib/src/cl_dynamic_array.svh
uvmgen/cluelib/src/cl_formatter.svh
uvmgen/cluelib/src/cl_global.svh
uvmgen/cluelib/src/cl_hex_formatter.svh
uvmgen/cluelib/src/cl_hex_min_formatter.svh
uvmgen/cluelib/src/cl_iterator.svh
uvmgen/cluelib/src/cl_journal.svh
uvmgen/cluelib/src/cl_kitchen_timer.svh
uvmgen/cluelib/src/cl_network.svh
uvmgen/cluelib/src/cl_packed_array.svh
uvmgen/cluelib/src/cl_pair.svh
uvmgen/cluelib/src/cl_pair_comparator.svh
uvmgen/cluelib/src/cl_pkg.sv
uvmgen/cluelib/src/cl_putil.svh
uvmgen/cluelib/src/cl_queue.svh
uvmgen/cluelib/src/cl_random_num.svh
uvmgen/cluelib/src/cl_route.svh
uvmgen/cluelib/src/cl_route_breadth_first_iterator.svh
uvmgen/cluelib/src/cl_route_node.svh
uvmgen/cluelib/src/cl_scrambler.svh
uvmgen/cluelib/src/cl_set.svh
uvmgen/cluelib/src/cl_set_base.svh
uvmgen/cluelib/src/cl_set_iterator.svh
uvmgen/cluelib/src/cl_string_formatter.svh
uvmgen/cluelib/src/cl_text.svh
uvmgen/cluelib/src/cl_tree.svh
uvmgen/cluelib/src/cl_tree_breadth_first_iterator.svh
uvmgen/cluelib/src/cl_tree_node.svh
uvmgen/cluelib/src/cl_tuple.svh
uvmgen/cluelib/src/cl_tuple_comparator.svh
uvmgen/cluelib/src/cl_types.svh
uvmgen/cluelib/src/cl_unpacked_array.svh
uvmgen/cluelib/src/cl_util.svh
uvmgen/cluelib/src/overview.txt
uvmgen/svlib/svlib/src/raw-sv-header
uvmgen/svlib/svlib/src/svlib.f
uvmgen-0.7.1.dist-info/METADATA
uvmgen-0.7.1.dist-info/WHEEL
uvmgen-0.7.1.dist-info/entry_points.txt
uvmgen-0.7.1.dist-info/top_level.txt
uvmgen-0.7.1.dist-info/RECORD
